flexdi/__init__.py
flexdi/_bindable.py
flexdi/_entrypoint.py
flexdi/_graph.py
flexdi/_implicit.py
flexdi/_openable.py
flexdi/_resolvable.py
flexdi/_rules.py
flexdi/_scope.py
flexdi/_store.py
flexdi/_types.py
flexdi/_util.py
flexdi/errors.py
flexdi/py.typed
flexdi/fastapi/__init__.py
flexdi/flask/__init__.py
flexdi/grpc/__init__.py
flexdi-0.3.0.dist-info/LICENSE
flexdi-0.3.0.dist-info/METADATA
flexdi-0.3.0.dist-info/WHEEL
flexdi-0.3.0.dist-info/top_level.txt
flexdi-0.3.0.dist-info/RECORD
