Metadata-Version: 2.1
Name: flexdi
Version: 0.3.0
Summary: A flexible dependency injection tool for typed Python projects.
Home-page: https://github.com/cal-pratt/flexdi
Author: Cal Pratt
Author-email: ccpratt4@gmail.com
License: MIT
Classifier: Programming Language :: Python :: 3.8
Classifier: Programming Language :: Python :: 3.9
Classifier: Programming Language :: Python :: 3.10
Classifier: Programming Language :: Python :: 3.11
Requires-Python: >=3.8
License-File: LICENSE
Requires-Dist: typing-extensions (>=4)
Provides-Extra: grpc
Requires-Dist: grpc-interceptor (>=0.15) ; extra == 'grpc'
Requires-Dist: grpcio (>=1.44) ; extra == 'grpc'
